{
    "status": "ok",
    "totalResults": 1126,
    "articles": [
        {
            "source": {
                "id": null,
                "name": "The Indian Express"
            },
            "author": "Express Web Desk",
            "title": "Sensex slips 130 pts, Nifty down to 18,733; IndusInd Bank, Infosys, TCS lose",
            "description": "IT stocks were the biggest losers in the opening trade, dragging the indices, after JP Morgan reiterated its negative stance on Indian information technology (IT) services.",
            "url": "https://indianexpress.com/article/business/market/stock-market-live-sensex-nifty-indusind-tcs-infosys-8663687/",
            "urlToImage": "https://images.indianexpress.com/2023/06/sensexbloomberg-1.jpg",
            "publishedAt": "2023-06-15T04:18:47Z",
            "content": "Domestic equities opened lower on Thursday despite Federal Reserve keeping the key policy rate unchanged. BSE benchmark Sensex opened 96.66 points, or 0.15 per cent lower to 63,131.85, while broader … [+979 chars]"
        },
        {
            "source": {
                "id": null,
                "name": "The Indian Express"
            },
            "author": "ENS Economic Bureau",
            "title": "Sensex, Nifty touch fresh highs on FII inflows, global cues",
            "description": "The BSE Sensex surged 803 points, or 1.26 per cent, to close at an all-time high of 64,718.56. The broader Nifty gained 216.95 points, or 1.14 per cent, to a fresh peak of 19,189.05. During the previous week, Sensex rose by over 1,700 points.",
            "url": "https://indianexpress.com/article/business/market/sensex-nifty-touch-fresh-highs-on-fii-inflows-global-cues-8695121/",
            "urlToImage": "https://images.indianexpress.com/2023/07/bse-bombay-stock-exchange-bloomberg-1200-1.jpg",
            "publishedAt": "2023-06-30T22:51:05Z",
            "content": "Domestic stock markets rose over 1 per cent to end at record highs on Friday, aided by robust inflows from foreign investors, positive global data and progress in monsoon.The BSE Sensex surged 803 po… [+2630 chars]"
        },
        {
            "source": {
                "id": null,
                "name": "The Indian Express"
            },
            "author": "Express News Service",
            "title": "‘Won’t give inch of land’: Farmers’ body on goods train project in Surat",
            "description": "A total of 34 farmers from Ichhapore, 34 from Damka, 35 from Vanswa, and around 10 from Olpad are majorly affected.",
            "url": "https://indianexpress.com/article/cities/ahmedabad/surat-goods-train-project-khedut-samaj-gujarat-8752709/",
            "urlToImage": "https://images.indianexpress.com/2023/07/pune-farmers.jpg",
            "publishedAt": "2023-07-05T01:00:52Z",
            "content": "At massive gatherings that saw attendees from 17 villages in Olpad and Choryasi taluka of Surat district, farmers decided not to give their land for the central government’s goods train project betwe… [+2147 chars]"
        },
        {
            "source": {
                "id": null,
                "name": "The Indian Express"
            },
            "author": "PTI",
            "title": "RBI must repeal notification allowing banks to undertake compromise settlement of wilful defaults: Cong",
            "description": "Addressing a press conference at the AICC headquarters here, AICC secretary Vineet Punia and Congress leader Amitabh Dubey said the financial burden on this country from fraud and wilful defaults has been severe.",
            "url": "https://indianexpress.com/article/cities/delhi/rbi-repeal-notification-allowing-banks-undertake-compromise-settlement-wilful-defaults-cong-8662769/",
            "urlToImage": "https://images.indianexpress.com/2023/06/JR.jpg",
            "publishedAt": "2023-06-14T10:32:02Z",
            "content": "The Congress on Wednesday attacked the Centre over the Reserve Bank of India allowing banks to go for a compromise settlement of fraud accounts and wilful defaults and demanded that the central bank … [+4686 chars]"
        },
        {
            "source": {
                "id": null,
                "name": "The Indian Express"
            },
            "author": "Express News Service",
            "title": "‘Why is Rahul Gandhi hobnobbing with those funded by George Soros?’: Smriti Irani after FIR against Amit Malviya",
            "description": "Union minister Smriti Irani raised questions about Rahul Gandhi’s meetings during his recent US visit and reiterated that the Congress had taken support from people with links to billionaire investor George Soros.",
            "url": "https://indianexpress.com/article/india/rahul-gandhi-hobobbing-george-soros-smriti-irani-8691841/",
            "urlToImage": "https://images.indianexpress.com/2023/06/Smriti-Irani-1.jpeg",
            "publishedAt": "2023-06-29T04:20:38Z",
            "content": "Hitting out at the Congress over the registration of an FIR against itsIT cell head Amit Malviya in Karnataka, the BJP on Wednesday alleged that Opposition leader Rahul Gandhi had hobnobbed with the … [+3316 chars]"
        },
        {
            "source": {
                "id": null,
                "name": "The Indian Express"
            },
            "author": "Explained Desk",
            "title": "George Soros’s son takes over the $25 billion family empire: Who is Alexander Soros?",
            "description": "Soros’s younger son, Alexander, has said he plans to continue backing left-leaning US politicians as his father did, in an interview with The Wall Street Journal.",
            "url": "https://indianexpress.com/article/explained/george-soros-son-takes-over-alexander-soros-8658209/",
            "urlToImage": "https://images.indianexpress.com/2023/06/WhatsApp-Image-2023-06-12-at-11.16.03.jpeg",
            "publishedAt": "2023-06-12T05:53:50Z",
            "content": "Billionaire American investor George Soros, who is known for funding left-wing and liberal causes at home and abroad, has handed over the reins of his fortune to his younger son Alexander Soros.In an… [+5699 chars]"
        },
        {
            "source": {
                "id": "the-times-of-india",
                "name": "The Times of India"
            },
            "author": "ET Bureau",
            "title": "Adani set to acquire online train booking platform Trainman",
            "description": "\"Adani Digital Labs, a wholly owned subsidiary of the company, has signed a share purchase agreement in relation to its proposed acquisition of 100% stake in Stark Enterprises,\" read a stock exchange notification from Adani Enterprises.",
            "url": "https://economictimes.indiatimes.com/industry/transportation/railways/adani-set-to-acquire-online-train-booking-platform-trainman/articleshow/101056744.cms",
            "urlToImage": "https://img.etimg.com/thumb/msid-101053149,width-1070,height-580,imgsize-33504,overlay-etmarkets/photo.jpg",
            "publishedAt": "2023-06-16T19:09:56Z",
            "content": "Adani Enterprises, the flagship business of the Adani Group, said on Friday it would acquire 100% equity in Stark Enterprises (SEPL), which operates online train booking platform Trainman.The company… [+1757 chars]"
        },
        {
            "source": {
                "id": "the-times-of-india",
                "name": "The Times of India"
            },
            "author": "Vidya Sreedhar",
            "title": "Fitch affirms Adani Green RG rating at BBB-, with stable outlook",
            "description": "The restricted group's financial profile with debt-service coverage ratio (DSCR) of 1.44 times is stronger than that commensurate with a 'BBB-' rating for the asset portfolio. This reflects considerable rating headroom at the current level, Fitch said.",
            "url": "https://economictimes.indiatimes.com/markets/stocks/news/fitch-affirms-adani-green-rg-rating-at-bbb-with-stable-outlook/articleshow/101038834.cms",
            "urlToImage": "https://img.etimg.com/thumb/msid-101038787,width-1070,height-580,imgsize-70912,overlay-etmarkets/photo.jpg",
            "publishedAt": "2023-06-16T07:04:57Z",
            "content": "MUMBAI - Fitch Ratings on Friday affirmed its BBB- rating on Adani Green Energy Restricted Group 2's $362.5 million senior secured notes, and retained a stable outlook. The credit assessment is suppo… [+2512 chars]"
        },
        {
            "source": {
                "id": "the-times-of-india",
                "name": "The Times of India"
            },
            "author": "Rajesh Mascarenhas",
            "title": "Rejig of FTSE indices could see net inflow of $150-200 million",
            "description": "​​Wipro is expected to get $32 million whereas Punjab National Bank, Bajaj Finance, Varun Beverages, and Adani Transmission could see inflow of $20 million each. Infosys, HCL Tech, and Equitas Small Finance could see an outflow between $13 million and $34 mil…",
            "url": "https://economictimes.indiatimes.com/markets/stocks/news/rejig-of-ftse-indices-could-see-net-inflow-of-150-200-million/articleshow/101030615.cms",
            "urlToImage": "https://img.etimg.com/thumb/msid-101030618,width-1070,height-580,imgsize-140089,overlay-etmarkets/photo.jpg",
            "publishedAt": "2023-06-16T00:09:39Z",
            "content": "Global index services provider FTSE is to rejig its indices on Friday which could lead to a net inflow of $150-200 million into various stocks. Adani Enterprises, Reliance Industries, Wipro, Punjab N… [+858 chars]"
        }
    ]
}